{ "Book": {"Id": "54", "Title": "El Evangelio del Asesino", "Authors": [ 39 ], "Genres": [ "THRILLER / TERROR"], "Synopsis": "Las vacaciones del detective Emmett Montgomery han terminado, pero los asesinatos no. Después de pasar un tiempo con su familia por las festividades de Navidad y hacer algunas actividades en su apartamento para pasar el rato, es hora de volver a la acción.<br /><br />Un asesino acecha la ciudad de Silveroak y es el trabajo del detective Montgomery y de su compañera Brenda Fox desentrañar el misterio de estas muertes. Así es como este dúo de detectives se adentrará en los lugares más oscuros de la ciudad para encontrar la verdad detrás de estas muertes.<br /><br />¿Quién es el asesino? ¿Se trata de uno solo o son más? ¿Por qué lo hace? Son preguntas que le corresponde responder a los detectives Montgomery y Fox.", "Cover": "81xSZ96HZNL", "Networks": "", "ASIN": "B0DWP4F4ZD"}}
