{ "Book": { "Id": "93", "Title": "Los diablillos de Georgia", "Authors": [ 58 ], "Genres": [ "OTROS" ], "Synopsis": "¿Puede una ciudad olvidar lo que sus raíces aún recuerdan? Mariam vuelve a Kutaisi para conmemorar el año del fallecimiento de su abuelo, sin darse cuenta de que el pasado nunca olvida. Y es que cuenta la leyenda que cada vez que hay luna llena, Georgia se llena de susurros y risas que provienen de los diablillos de la noche. ¿Qué harías tú si los cuentos que olvidaste te estuvieran esperando? Bienvenidos a Georgia…", "Cover": "/books/1759392680i/242308544", "Networks": "", "Bases": [ { "ASIN": "B0FTK8W868", "Base": "AMAZON" }]}}
