{ "Book": { "Id": "9", "Title": "El Fulgor: Catastropha 1", "Authors": [ 35 ], "Genres": [ "OTROS" ], "Synopsis": "«Durante el Baile de Primavera, cuando la paz reina en el Ducado, un incendio devasta la mansión. Una extraña pareja murmura entre cortinajes. El caos corre como la pólvora y no hay escapatoria posible del infierno. Seis meses antes los engranajes de una armonía confusa encajan mientras la Duquesa se adapta a sus cercanos treinta años. Los gemelos Casio y Owen son incapaces de ocultar el desprecio mutuo. Los hermanos Lisitsa dividen sus caminos y Libelle se preocupa por un secreto que no debería haber descubierto. La cuenta atrás ha comenzado. ¿Cómo se inició el incendio? ¿Quién es el culpable? ¿Quién sobrevivirá?»", "Cover": "/books/1743582668i/230870199", "Networks": "", "Bases": [ { "ASIN": "B0BC4DQ5GQ", "Base": "AMAZON" }]}}
